dotcp/__init__.py
dotcp/__main__.py
dotcp/cli.py
dotcp/config.py
dotcp-0.1.1.dist-info/entry_points.txt
dotcp-0.1.1.dist-info/WHEEL
dotcp-0.1.1.dist-info/METADATA
dotcp-0.1.1.dist-info/license_files/LICENSE
dotcp-0.1.1.dist-info/RECORD
