Metadata-Version: 2.1
Name: dotcp
Version: 0.1.1
Summary: copy selected dotfiles to directory
License: MIT
Keywords: dotfiles
Author-email: jieggii <jieggii.contact@gmail.com>
Requires-Python: >=3.6.2
Project-URL: Bug Tracker, https://github.com/jieggii/dotcp/issues
Project-URL: Homepage, https://github.com/jieggii/dotcp
